rm_unneeded_f_str.py
rm_unneeded_f_str-0.2.0.dist-info/LICENSE
rm_unneeded_f_str-0.2.0.dist-info/METADATA
rm_unneeded_f_str-0.2.0.dist-info/WHEEL
rm_unneeded_f_str-0.2.0.dist-info/entry_points.txt
rm_unneeded_f_str-0.2.0.dist-info/top_level.txt
rm_unneeded_f_str-0.2.0.dist-info/RECORD
