Metadata-Version: 2.1
Name: rm-unneeded-f-str
Version: 0.2.0
Summary: Find and replace unneeded f-strings in your code.
Home-page: https://github.com/dannysepler/rm_unneeded_f_str
Author: Danny Sepler
Author-email: dannysepler@gmail.com
License: MIT
Classifier: License :: OSI Approved :: MIT License
Classifier: Programming Language :: Python :: 3
Classifier: Programming Language :: Python :: 3 :: Only
Requires-Python: >=3.7
License-File: LICENSE
